{
    "move": {
        "string_id": "move",
        "functions": [
            {
                "script_name": "DoNothing",
                "value_pairs": {
                    "where_to_load": "OnEnded"
                }
            }
        ],
        "component_ints": {},
        "component_strings": {},
        "component_floats": {},
        "job_time": 0,
        "allowed_sqr_dist": 0
    },
    "build_tile": {
        "string_id": "build_tile",
        "functions": [
            {
                "script_name": "SetTileType",
                "value_pairs": {
                    "where_to_load": "OnEnded"
                }
            }
        ],
        "component_ints": {},
        "component_strings": { "tile_type": "stone_rough" },
        "component_floats": {},
        "job_object_id": "tile_type",
        "job_time": 1,
        "allowed_sqr_dist": 2
    },
    "build_furniture": {
        "string_id": "build_furniture",
        "functions": [
            {
                "script_name": "BuildFurniture",
                "value_pairs": {
                    "where_to_load": "OnEnded"
                }
            }
        ],
        "component_ints": {},
        "component_strings": { "furniture_type": "wall_wood" },
        "component_floats": {},
        "job_object_id": "furniture_type",
        "job_time": 1,
        "allowed_sqr_dist": 2
    }
}